pylint_message_id.py
pylint_message_id-0.1.dist-info/LICENSE
pylint_message_id-0.1.dist-info/METADATA
pylint_message_id-0.1.dist-info/WHEEL
pylint_message_id-0.1.dist-info/top_level.txt
pylint_message_id-0.1.dist-info/RECORD
